microngo/__init__.py
microngo/microngo.py
microngo/pagination.py
Microngo-0.1.1.dist-info/LICENSE
Microngo-0.1.1.dist-info/METADATA
Microngo-0.1.1.dist-info/WHEEL
Microngo-0.1.1.dist-info/top_level.txt
Microngo-0.1.1.dist-info/RECORD
