Metadata-Version: 2.1
Name: Microngo
Version: 0.1.1
Summary: Microngo is small, fast, and lightweight MongoDB toolkit for python
Home-page: https://microngo.emsuryadi.com/
Author: Em Suryadi
Author-email: me@emsuryadi.com
License: MIT
Platform: UNKNOWN
Classifier: Development Status :: 3 - Alpha
Classifier: Intended Audience :: Developers
Classifier: License :: OSI Approved :: MIT License
Classifier: Operating System :: OS Independent
Classifier: Programming Language :: Python
Classifier: Topic :: Database
Classifier: Topic :: Software Development :: Libraries :: Python Modules
Requires-Dist: pymongo (>=3.7.0)
